shellcord/__init__.py
shellcord/cli.py
shellcord/config.py
shellcord/generator.py
shellcord/scord.py
shellcord-0.2.0.dist-info/entry_points.txt
shellcord-0.2.0.dist-info/WHEEL
shellcord-0.2.0.dist-info/METADATA
shellcord-0.2.0.dist-info/RECORD
