Metadata-Version: 2.1
Name: shellcord
Version: 0.2.0-3dev0
Summary: Easily create runbooks from your shell commands
Home-page: https://github.com/bnichs/shellcord.git
License: MIT
Keywords: runbook,shell
Author: Ben
Author-email: bnichs55@gmail.com
Requires-Python: >=3.7,<4.0
Classifier: Development Status :: 3 - Alpha
Classifier: Environment :: Console
Classifier: Intended Audience :: Developers
Classifier: License :: OSI Approved :: MIT License
Classifier: Operating System :: OS Independent
Classifier: Programming Language :: Python :: 3
Classifier: Programming Language :: Python :: 3.7
Classifier: Programming Language :: Python :: 3.8
Classifier: Programming Language :: Python :: 3.9
Classifier: Programming Language :: Python :: 3.10
Classifier: Programming Language :: Python :: 3
Classifier: Topic :: System :: Shells
Requires-Dist: click (>=8.0.3,<9.0.0)
Requires-Dist: flake8 (>=4.0.1,<5.0.0)
Requires-Dist: pytest (>=7.0.1,<8.0.0)
Requires-Dist: pytest-cov (>=3.0.0,<4.0.0)
Project-URL: Repository, https://github.com/bnichs/shellcord.git
